querify/__init__.py
querify/errors.py
querify/querify.py
querify-0.1.0.dist-info/DESCRIPTION.rst
querify-0.1.0.dist-info/METADATA
querify-0.1.0.dist-info/RECORD
querify-0.1.0.dist-info/WHEEL
querify-0.1.0.dist-info/metadata.json
querify-0.1.0.dist-info/top_level.txt
