Metadata-Version: 2.0
Name: querify
Version: 0.1.0
Summary: InfluxQL / MySQL / Mongo query generator from json-represented filters (mongodb-like query objects)
Home-page: https://github.com/Raychee/querify
Author: Raychee Zhang
Author-email: raychee.zhang@gmail.com
License: MIT
Download-URL: https://github.com/Raychee/querify/tarball/0.1.0
Keywords: json,mongo,influx,mysql,query
Platform: UNKNOWN
Classifier: Development Status :: 4 - Beta
Classifier: Intended Audience :: Developers
Classifier: Framework :: Pytest
Classifier: License :: OSI Approved :: MIT License
Classifier: Natural Language :: English
Classifier: Programming Language :: Python :: 3
Classifier: Programming Language :: Python :: 3.5
Classifier: Programming Language :: Python :: 3.6
Classifier: Programming Language :: Python :: 3 :: Only
Classifier: Topic :: Software Development :: Libraries
Classifier: Topic :: Software Development :: Libraries :: Python Modules
Classifier: Topic :: Utilities
Requires-Python: >=3.5
Requires-Dist: qutils (>=0.3.0)
